[
    {
        "title": "กรุงเทพฯ เป็นเมืองหลวงของประเทศใด",
        "option": ["ประเทศไทย", "เวียดนาม", "มาเลเซีย", "อินโดนีเซีย"],
        "answer": 1
    },
    {
        "title": "ข้อใดคือชื่อประเทศที่ใช้ภาษาสเปนเป็นภาษาราชการ",
        "option": ["ฝรั่งเศส", "เม็กซิโก", "เยอรมัน", "อิตาลี"],
        "answer": 2
    },
    {
        "title": "ดวงดาวที่ใกล้โลกที่สุดคืออะไร",
        "option": ["ดวงจันทร์", "ดาวอังคาร", "ดวงอาทิตย์", "ดาวพฤหัสบดี"],
        "answer": 3
    },
    {
        "title": "มะพร้าวเป็นผลไม้ชนิดใด",
        "option": ["ผลไม้ประเภทถั่ว", "ผลไม้ประเภทผัก", "ผลไม้ประเภทเมล็ด", "ผลไม้ประเภทกะทิ"],
        "answer": 3
    },
    {
        "title": "การประท้วงในเดือนตุลาคม 1973 ที่ประเทศไทยเรียกว่าอะไร",
        "option": ["เหตุการณ์ 14 ตุลา", "เหตุการณ์ 6 ตุลา", "เหตุการณ์ 16 ตุลา", "เหตุการณ์ 19 พฤษภา"],
        "answer": 1
    },
    {
        "title": "มหาวิทยาลัยแห่งแรกของประเทศไทยคือที่ไหน",
        "option": ["จุฬาลงกรณ์มหาวิทยาลัย", "มหาวิทยาลัยมหิดล", "มหาวิทยาลัยธรรมศาสตร์", "มหาวิทยาลัยเชียงใหม่"],
        "answer": 1
    },
    {
        "title": "การฟื้นฟูธรรมชาติในป่าไม้เรียกว่าอะไร",
        "option": ["การปลูกป่า", "การตัดไม้", "การอนุรักษ์ป่า", "การทำเหมือง"],
        "answer": 1
    },
    {
        "title": "สิ่งที่สำคัญที่สุดในการสร้างเมืองที่ยั่งยืนคืออะไร",
        "option": ["การรักษาสิ่งแวดล้อม", "การพัฒนาเศรษฐกิจ", "การสร้างโครงสร้างพื้นฐาน", "การเพิ่มการท่องเที่ยว"],
        "answer": 1
    },
    {
        "title": "สัตว์ชนิดใดที่มีการเดินทางในท้องทะเลไปยังทะเลที่มีอุณหภูมิสูง",
        "option": ["ปลาโลมา", "วาฬ", "ฉลาม", "กุ้ง"],
        "answer": 2
    },
    {
        "title": "ประเทศไทยมีชายฝั่งทะเลยาวกี่กิโลเมตร",
        "option": ["ประมาณ 2,500 กิโลเมตร", "ประมาณ 4,500 กิโลเมตร", "ประมาณ 5,500 กิโลเมตร", "ประมาณ 6,500 กิโลเมตร"],
        "answer": 1
    },
    {
        "title": "วิทยาศาสตร์สาขาไหนที่ศึกษาเกี่ยวกับสิ่งมีชีวิตในระบบนิเวศ",
        "option": ["ชีววิทยา", "ฟิสิกส์", "เคมี", "ธรณีวิทยา"],
        "answer": 1
    },
    {
        "title": "เครื่องมือที่ใช้ในการวัดอุณหภูมิเรียกว่าอะไร",
        "option": ["เทอร์โมมิเตอร์", "บารอมิเตอร์", "เฮดมิเตอร์", "แคลมิเตอร์"],
        "answer": 1
    },
    {
        "title": "ใครเป็นผู้ประดิษฐ์เครื่องพิมพ์ดีด",
        "option": ["อเล็กซานเดอร์ แกรม เบลล์", "โธมัส เอดิสัน", "คริสโตเฟอร์ โคลัมบัส", "คริสตอฟเฟอร์ โพลโล"],
        "answer": 2
    },
    {
        "title": "เมื่อปีไหนที่ไทยได้จัดงานเอเชียนเกมส์ครั้งแรก",
        "option": ["1970", "1978", "1982", "1990"],
        "answer": 2
    },
    {
        "title": "โครงสร้างของอวัยวะที่สำคัญในระบบทางเดินหายใจคืออะไร",
        "option": ["ปอด", "หัวใจ", "หลอดเลือด", "กระเพาะอาหาร"],
        "answer": 1
    }
]
